{
  "skill_version": "v1",
  "seed": {
    "seed_id": "seed_0023",
    "panel_role": "budget_constrained",
    "age_band": "25-34",
    "location_type": "suburban",
    "household_structure": "living with roommates",
    "occupation_band": "field_service",
    "income_band": "lower_middle",
    "education_band": "postgraduate",
    "language": [
      "Cantonese",
      "English"
    ],
    "device_environment": "multi-device",
    "payment_environment": "careful subscription user",
    "schedule_pressure": "low",
    "budget_flexibility": "low",
    "caregiving_load": "low",
    "trust_threshold": "needs_trial",
    "switching_cost_level": "medium",
    "privacy_risk_tolerance": "medium",
    "digital_literacy_ceiling": "medium",
    "locale_pack": "new_territories_operator",
    "life_stage": "caregiver_balancing_work",
    "purchase_authority_type": "shared_household_decider",
    "employment_stability": "contract_based",
    "workflow_maturity": "documented",
    "decision_speed": "committee_slow",
    "proof_threshold": "peer_reference_required",
    "cash_flow_volatility": "medium"
  },
  "decision_policy": {
    "adoption_style": "adopts when the payoff is concrete and the risk feels bounded",
    "trust_requirements": [
      "clear before-and-after value",
      "low-friction onboarding"
    ],
    "rejection_triggers": [
      "extra admin burden",
      "vague claims without proof",
      "subscription cost that grows before value is obvious"
    ],
    "proof_requirements": [
      "specific examples from similar users",
      "a short trial workflow",
      "simple ROI signal within the first week",
      "buy-in material that can be shared with other decision-makers"
    ]
  },
  "response_style": {
    "articulation_level": "medium",
    "directness": "high",
    "detail_tendency": "medium"
  },
  "audit": {
    "persona_generation_method": "deterministic_seed_plus_template_enrichment_v1",
    "evidence_grade": "synthetic_seeded",
    "source_basis": [
      "panel_frame",
      "seed_constraints",
      "trait_catalogs",
      "template_enrichment"
    ],
    "stereotype_risk_score": 3,
    "synthetic_only_disclaimer": "Synthetic persona for AI pre-validation only.",
    "do_not_use_for": [
      "employment screening",
      "credit or insurance decisions",
      "medical guidance",
      "legal guidance",
      "discriminatory targeting"
    ],
    "last_audited_at": "2026-06-17",
    "persona_version": "v1",
    "diversity_dimensions": [
      "panel_role",
      "locale_pack",
      "life_stage",
      "purchase_authority_type",
      "workflow_maturity",
      "cash_flow_volatility"
    ]
  }
}