[
  {
    "synthetic_user_id": "su_0003",
    "name": "Devon Chu",
    "age": 59,
    "gender": "non-binary",
    "location": "Kaohsiung",
    "language": [
      "Mandarin"
    ],
    "locale_pack": "taiwan knowledge work",
    "occupation": "finance manager",
    "education_level": "bachelor",
    "income_level": "middle",
    "marital_status": "single",
    "family_structure": "living alone",
    "household_size": 1,
    "living_area": "regional",
    "housing_status": "renting",
    "life_stage": "retention skeptic"
  },
  {
    "synthetic_user_id": "su_0002",
    "name": "Rina Mak",
    "age": 53,
    "gender": "woman",
    "location": "Hong Kong",
    "language": [
      "Cantonese",
      "English"
    ],
    "locale_pack": "hong kong smb",
    "occupation": "program manager",
    "education_level": "diploma",
    "income_level": "upper_middle",
    "marital_status": "single",
    "family_structure": "living alone",
    "household_size": 1,
    "living_area": "urban_core",
    "housing_status": "owner-occupier",
    "life_stage": "mid career operator"
  },
  {
    "synthetic_user_id": "su_0001",
    "name": "Reese Teo",
    "age": 46,
    "gender": "non-binary",
    "location": "Kaohsiung",
    "language": [
      "Mandarin"
    ],
    "locale_pack": "taiwan knowledge work",
    "occupation": "program manager",
    "education_level": "diploma",
    "income_level": "middle",
    "marital_status": "single",
    "family_structure": "living with parents",
    "household_size": 3,
    "living_area": "regional",
    "housing_status": "owner-occupier",
    "life_stage": "mid career operator"
  }
]